moodle/__init__.py
moodle/constants.py
moodle/exceptions.py
moodle/py.typed
moodle/session.py
moodle/util.py
moodle/contrib/__init__.py
moodle/contrib/identityproviders.py
pymoodle-0.3.2.dist-info/LICENSE
pymoodle-0.3.2.dist-info/METADATA
pymoodle-0.3.2.dist-info/WHEEL
pymoodle-0.3.2.dist-info/top_level.txt
pymoodle-0.3.2.dist-info/RECORD
